<?xml version="1.0" encoding="utf-8"?>
<result>
    <data_file_name>call2.txt</data_file_name>
    <bottleneck_V>1.1363e-07 2.0691e-07 1.1483e-08 1.8829e-07 1.9672e-10 8.1387e-10 4.5653e-08 3.2696e-08 1.3643e-08
        1.4621e-09
    </bottleneck_V>
    <bottleneck_T>0.249921 69.9737 0.00998053 5.29832 7.37228e-06 0.0037075 0.0564621 1.63336 0.128892 0.0270664
    </bottleneck_T>
    <bottleneck_L>971151.19553 6026268.9179 93555.594557 513392.24329 0.11561574079 278.9788438 65750.651232
        711334.51234 137714.92504 8815.8556735
    </bottleneck_L>
    <reliability>0.9896</reliability>
</result>